db2model/__init__.py
db2model/cli.py
db2model/types.py
db2model/config/__init__.py
db2model/config/settings.py
db2model/generator/__init__.py
db2model/generator/python/__init__.py
db2model/generator/python/constants.py
db2model/generator/python/files.py
db2model/generator/python/generator.py
db2model/generator/python/parser.py
db2model/generator/python/raw.py
db2model/generator/python/table.py
db2model/generator/python/utils.py
db2model/models/__init__.py
db2model/models/table_def.py
db2model/models/table_import.py
db2model-0.1.11.dist-info/METADATA
db2model-0.1.11.dist-info/WHEEL
db2model-0.1.11.dist-info/entry_points.txt
db2model-0.1.11.dist-info/licenses/LICENSE
db2model-0.1.11.dist-info/RECORD
