Metadata-Version: 2.4
Name: db2model
Version: 0.1.11
Summary: Generate typed models from your database for Python, Go, and TypeScript.
Project-URL: Homepage, https://github.com/AlixPa/db2model
Project-URL: Source, https://github.com/AlixPa/db2model
Project-URL: Bug Tracker, https://github.com/AlixPa/db2model/issues
Author-email: Alix Paradis <alix.paradis00@gmail.com>
License-Expression: MIT
License-File: LICENSE
Keywords: codegen,db,golang,models,sqlalchemy,typescript
Classifier: Operating System :: OS Independent
Classifier: Programming Language :: Python :: 3
Classifier: Programming Language :: Python :: 3.10
Classifier: Programming Language :: Python :: 3.11
Classifier: Programming Language :: Python :: 3.12
Classifier: Programming Language :: Python :: 3.13
Classifier: Programming Language :: Python :: 3.14
Requires-Python: >=3.10
Requires-Dist: autoflake>=2.3.0
Requires-Dist: black>=24.8.0
Requires-Dist: geoalchemy2>=0.14.3
Requires-Dist: isort>=7.0.0
Requires-Dist: pydantic-settings>=0.8.0
Requires-Dist: python-dotenv>=1.2.0
Requires-Dist: sqlacodegen>=3.0.0
Requires-Dist: sqlalchemy>=2.0
Requires-Dist: typer>=0.15.0
